ait/core/__init__.py
ait/core/api.py
ait/core/bin/__init__.py
ait/core/bin/ait_bsc.py
ait/core/bin/ait_bsc_create_handler.py
ait/core/bin/ait_bsc_stop_handler.py
ait/core/bin/ait_ccsds_send_example.py
ait/core/bin/ait_cmd_hist.py
ait/core/bin/ait_cmd_send.py
ait/core/bin/ait_create_dirs.py
ait/core/bin/ait_dict_writer.py
ait/core/bin/ait_limits_find_dn.py
ait/core/bin/ait_mps_seq_convert.py
ait/core/bin/ait_pcap.py
ait/core/bin/ait_pcap_segment.py
ait/core/bin/ait_seq_decode.py
ait/core/bin/ait_seq_encode.py
ait/core/bin/ait_seq_print.py
ait/core/bin/ait_seq_send.py
ait/core/bin/ait_server.py
ait/core/bin/ait_table_decode.py
ait/core/bin/ait_table_encode.py
ait/core/bin/ait_tlm_csv.py
ait/core/bin/ait_tlm_db_insert.py
ait/core/bin/ait_tlm_send.py
ait/core/bin/ait_tlm_simulate.py
ait/core/bin/ait_yaml_validate.py
ait/core/bsc.py
ait/core/ccsds.py
ait/core/cfg.py
ait/core/cmd.py
ait/core/coord.py
ait/core/data/cmd_schema.json
ait/core/data/evr_schema.json
ait/core/data/limits_schema.json
ait/core/data/table_schema.json
ait/core/data/tlm_schema.json
ait/core/db.py
ait/core/dmc.py
ait/core/dtype.py
ait/core/evr.py
ait/core/gds.py
ait/core/geom.py
ait/core/json.py
ait/core/limits.py
ait/core/log.py
ait/core/notify.py
ait/core/pcap.py
ait/core/py.typed
ait/core/seq.py
ait/core/server/__init__.py
ait/core/server/broker.py
ait/core/server/client.py
ait/core/server/config.py
ait/core/server/handler.py
ait/core/server/handlers/__init__.py
ait/core/server/handlers/ccsds_packet_handler.py
ait/core/server/handlers/packet_handler.py
ait/core/server/plugin.py
ait/core/server/plugins/PacketAccumulator.py
ait/core/server/plugins/PacketPadder.py
ait/core/server/plugins/__init__.py
ait/core/server/plugins/apid_routing.py
ait/core/server/plugins/data_archive.py
ait/core/server/plugins/limit_monitor.py
ait/core/server/plugins/openmct.py
ait/core/server/process.py
ait/core/server/server.py
ait/core/server/stream.py
ait/core/server/utils.py
ait/core/table.py
ait/core/tlm.py
ait_core-2.5.2.dist-info/LICENSE.txt
ait_core-2.5.2.dist-info/METADATA
ait_core-2.5.2.dist-info/WHEEL
ait_core-2.5.2.dist-info/entry_points.txt
ait_core-2.5.2.dist-info/RECORD
