Metadata-Version: 2.1
Name: ait-core
Version: 2.5.2
Summary: NASA JPL's Ground Data System toolkit for Instrument and CubeSat Missions
Home-page: https://github.com/NASA-AMMOS/AIT-Core
License: MIT
Author: AMMOS Instrument Toolkit Development Team
Author-email: ait-pmc@googlegroups.com
Requires-Python: >=3.7,<3.11
Classifier: License :: OSI Approved :: MIT License
Classifier: Programming Language :: Python :: 3
Classifier: Programming Language :: Python :: 3.7
Classifier: Programming Language :: Python :: 3.8
Classifier: Programming Language :: Python :: 3.9
Classifier: Programming Language :: Python :: 3.10
Requires-Dist: bottle (==0.12.23)
Requires-Dist: gevent
Requires-Dist: gevent-websocket (==0.10.1)
Requires-Dist: gipc (>=1.1.0,<2.0.0)
Requires-Dist: greenlet (==1.1.3)
Requires-Dist: jsonschema (==3.0.2)
Requires-Dist: pyyaml (==5.3.1)
Requires-Dist: pyzmq (==24.0.0)
Requires-Dist: requests (>=2.22.0)
Requires-Dist: setproctitle (>=1.2.3,<2.0.0)
Project-URL: Documentation, https://ait-core.readthedocs.io/en/latest
Project-URL: Repository, https://github.com/NASA-AMMOS/AIT-Core
